wntrfr/__init__.py
wntrfr/epanet/__init__.py
wntrfr/epanet/exceptions.py
wntrfr/epanet/io.py
wntrfr/epanet/toolkit.py
wntrfr/epanet/util.py
wntrfr/epanet/Darwin/libepanet.dylib
wntrfr/epanet/Darwin/libepanet22.dylib
wntrfr/epanet/Linux/libepanet22_amd64.so
wntrfr/epanet/Linux/libepanet2_amd64.so
wntrfr/epanet/Windows/epanet2.bas
wntrfr/epanet/Windows/epanet2.def
wntrfr/epanet/Windows/epanet2.dll
wntrfr/epanet/Windows/epanet2.lib
wntrfr/epanet/Windows/epanet2.pas
wntrfr/epanet/Windows/epanet22_amd64.dll
wntrfr/epanet/Windows/epanet22_win32.dll
wntrfr/epanet/Windows/epanet2_amd64.dll
wntrfr/gis/__init__.py
wntrfr/gis/geospatial.py
wntrfr/gis/network.py
wntrfr/graphics/__init__.py
wntrfr/graphics/color.py
wntrfr/graphics/curve.py
wntrfr/graphics/layer.py
wntrfr/graphics/network.py
wntrfr/metrics/__init__.py
wntrfr/metrics/economic.py
wntrfr/metrics/hydraulic.py
wntrfr/metrics/misc.py
wntrfr/metrics/topographic.py
wntrfr/metrics/water_security.py
wntrfr/morph/__init__.py
wntrfr/morph/link.py
wntrfr/morph/node.py
wntrfr/morph/skel.py
wntrfr/network/__init__.py
wntrfr/network/base.py
wntrfr/network/controls.py
wntrfr/network/elements.py
wntrfr/network/io.py
wntrfr/network/layer.py
wntrfr/network/model.py
wntrfr/network/options.py
wntrfr/scenario/__init__.py
wntrfr/scenario/earthquake.py
wntrfr/scenario/fragility_curve.py
wntrfr/sim/__init__.py
wntrfr/sim/core.py
wntrfr/sim/epanet.py
wntrfr/sim/hydraulics.py
wntrfr/sim/results.py
wntrfr/sim/solvers.py
wntrfr/sim/aml/__init__.py
wntrfr/sim/aml/_evaluator.cp312-win_amd64.pyd
wntrfr/sim/aml/aml.py
wntrfr/sim/aml/evaluator.cpp
wntrfr/sim/aml/evaluator.hpp
wntrfr/sim/aml/evaluator.i
wntrfr/sim/aml/evaluator.py
wntrfr/sim/aml/evaluator_wrap.cpp
wntrfr/sim/aml/expr.py
wntrfr/sim/aml/numpy.i
wntrfr/sim/models/__init__.py
wntrfr/sim/models/constants.py
wntrfr/sim/models/constraint.py
wntrfr/sim/models/param.py
wntrfr/sim/models/utils.py
wntrfr/sim/models/var.py
wntrfr/sim/network_isolation/__init__.py
wntrfr-1.1.0.1.3.dist-info/LICENSE.md
wntrfr-1.1.0.1.3.dist-info/METADATA
wntrfr-1.1.0.1.3.dist-info/WHEEL
wntrfr-1.1.0.1.3.dist-info/top_level.txt
wntrfr-1.1.0.1.3.dist-info/RECORD
