Metadata-Version: 2.2
Name: wntrfr
Version: 1.1.0.1.3
Summary: Water Network Tool for Resilience
Home-page: https://github.com/snaeimi/WNTR
Author: WNTR Developers
Maintainer-email: snaeimi@udel.edu
License: Revised BSD
License-File: LICENSE.md
Requires-Dist: numpy>=1.21
Requires-Dist: scipy
Requires-Dist: networkx
Requires-Dist: pandas
Requires-Dist: matplotlib
Requires-Dist: setuptools
Dynamic: author
Dynamic: description
Dynamic: home-page
Dynamic: license
Dynamic: maintainer-email
Dynamic: requires-dist
Dynamic: summary
